[
  {
    "team": "Penn",
    "score": 12.2603,
    "w": 13.5293,
    "l": -1.269
  },
  {
    "team": "Montana State",
    "score": 10.6866,
    "w": 12.0331,
    "l": -1.3465
  },
  {
    "team": "Bethune-Cookman",
    "score": 10.238,
    "w": 10.238,
    "l": 0
  },
  {
    "team": "Jackson State",
    "score": 10.1352,
    "w": 10.1352,
    "l": 0
  },
  {
    "team": "Southern Utah",
    "score": 8.9939,
    "w": 10.8608,
    "l": -1.8669
  },
  {
    "team": "Villanova",
    "score": 8.5878,
    "w": 10.1762,
    "l": -1.5884
  },
  {
    "team": "Jacksonville State",
    "score": 8.0722,
    "w": 9.8085,
    "l": -1.7363
  },
  {
    "team": "Incarnate Word",
    "score": 7.8462,
    "w": 9.7897,
    "l": -1.9435
  },
  {
    "team": "Maine",
    "score": 7.3056,
    "w": 9.0478,
    "l": -1.7422
  },
  {
    "team": "Long Island",
    "score": 7.0784,
    "w": 8.4259,
    "l": -1.3475
  },
  {
    "team": "Southern Illinois",
    "score": 7.0566,
    "w": 9.3153,
    "l": -2.2587
  },
  {
    "team": "Stony Brook",
    "score": 6.8537,
    "w": 8.1832,
    "l": -1.3295
  },
  {
    "team": "Florida A&M",
    "score": 6.6658,
    "w": 10.355,
    "l": -3.6892
  },
  {
    "team": "Dayton",
    "score": 6.3316,
    "w": 8.0923,
    "l": -1.7607
  },
  {
    "team": "Lehigh",
    "score": 6.2331,
    "w": 9.4982,
    "l": -3.2651
  },
  {
    "team": "St. Francis",
    "score": 6.0436,
    "w": 8.4766,
    "l": -2.433
  },
  {
    "team": "Dixie State",
    "score": 6.0238,
    "w": 9.8378,
    "l": -3.814
  },
  {
    "team": "Missouri State",
    "score": 5.7962,
    "w": 7.8732,
    "l": -2.077
  },
  {
    "team": "Delaware State",
    "score": 5.7305,
    "w": 8.6826,
    "l": -2.9521
  },
  {
    "team": "South Dakota State",
    "score": 5.6312,
    "w": 7.0455,
    "l": -1.4143
  },
  {
    "team": "Marist",
    "score": 5.4365,
    "w": 7.0874,
    "l": -1.6509
  },
  {
    "team": "Bryant",
    "score": 5.2672,
    "w": 7.8149,
    "l": -2.5477
  },
  {
    "team": "UC Davis",
    "score": 5.2054,
    "w": 8.4975,
    "l": -3.2921
  },
  {
    "team": "Butler",
    "score": 5.0233,
    "w": 7.6292,
    "l": -2.6059
  },
  {
    "team": "San Diego",
    "score": 4.9163,
    "w": 7.8419,
    "l": -2.9256
  },
  {
    "team": "Monmouth",
    "score": 4.8475,
    "w": 7.9492,
    "l": -3.1017
  },
  {
    "team": "Columbia",
    "score": 4.8221,
    "w": 6.7513,
    "l": -1.9292
  },
  {
    "team": "Lamar",
    "score": 4.4057,
    "w": 7.9144,
    "l": -3.5087
  },
  {
    "team": "Northern Iowa",
    "score": 4.3321,
    "w": 7.5618,
    "l": -3.2297
  },
  {
    "team": "Drake",
    "score": 4.3214,
    "w": 8.0948,
    "l": -3.7734
  },
  {
    "team": "Charleston Southern",
    "score": 4.1098,
    "w": 6.7664,
    "l": -2.6566
  },
  {
    "team": "Mercer",
    "score": 4.1028,
    "w": 7.9167,
    "l": -3.8139
  },
  {
    "team": "Wagner",
    "score": 4.0707,
    "w": 6.9754,
    "l": -2.9047
  },
  {
    "team": "Dartmouth",
    "score": 3.9578,
    "w": 6.5967,
    "l": -2.6389
  },
  {
    "team": "Mississippi Valley State",
    "score": 3.6383,
    "w": 9.0327,
    "l": -5.3944
  },
  {
    "team": "Tennessee State",
    "score": 3.5567,
    "w": 7.2751,
    "l": -3.7184
  },
  {
    "team": "Western Illinois",
    "score": 3.4196,
    "w": 6.5595,
    "l": -3.1399
  },
  {
    "team": "Cal Poly",
    "score": 3.318,
    "w": 7.7169,
    "l": -4.3989
  },
  {
    "team": "Presbyterian",
    "score": 3.2999,
    "w": 7.7322,
    "l": -4.4323
  },
  {
    "team": "Texas Southern",
    "score": 3.1294,
    "w": 7.8633,
    "l": -4.7339
  },
  {
    "team": "VMI",
    "score": 3.0127,
    "w": 7.3592,
    "l": -4.3465
  },
  {
    "team": "Towson",
    "score": 2.8523,
    "w": 6.2091,
    "l": -3.3568
  },
  {
    "team": "Northwestern State",
    "score": 2.8397,
    "w": 6.2827,
    "l": -3.443
  },
  {
    "team": "The Citadel",
    "score": 2.3943,
    "w": 6.2607,
    "l": -3.8664
  },
  {
    "team": "Alabama A&M",
    "score": 2.2622,
    "w": 6.3801,
    "l": -4.1179
  },
  {
    "team": "Murray State",
    "score": 2.0378,
    "w": 7.7749,
    "l": -5.7371
  },
  {
    "team": "Delaware",
    "score": 2.0348,
    "w": 5.3238,
    "l": -3.289
  },
  {
    "team": "Robert Morris",
    "score": 2.0196,
    "w": 6.78,
    "l": -4.7604
  },
  {
    "team": "Austin Peay",
    "score": 1.9049,
    "w": 8.0685,
    "l": -6.1636
  },
  {
    "team": "Indiana State",
    "score": 1.8352,
    "w": 3.5229,
    "l": -1.6877
  },
  {
    "team": "South Carolina State",
    "score": 1.6719,
    "w": 4.6343,
    "l": -2.9624
  },
  {
    "team": "Abilene Christian",
    "score": 1.631,
    "w": 3.734,
    "l": -2.103
  },
  {
    "team": "Yale",
    "score": 1.5033,
    "w": 6.2192,
    "l": -4.7159
  },
  {
    "team": "Harvard",
    "score": 1.4638,
    "w": 5.9811,
    "l": -4.5173
  },
  {
    "team": "Campbell",
    "score": 1.2372,
    "w": 5.6591,
    "l": -4.4219
  },
  {
    "team": "Valparaiso",
    "score": 1.116,
    "w": 5.019,
    "l": -3.903
  },
  {
    "team": "McNeese State",
    "score": 0.9171,
    "w": 5.577,
    "l": -4.6599
  },
  {
    "team": "Southeastern Louisiana",
    "score": 0.7335,
    "w": 5.4398,
    "l": -4.7063
  },
  {
    "team": "Davidson",
    "score": 0.6923,
    "w": 5.5583,
    "l": -4.866
  },
  {
    "team": "Samford",
    "score": 0.5978,
    "w": 6.5966,
    "l": -5.9988
  },
  {
    "team": "Tennessee Tech",
    "score": 0.5611,
    "w": 5.3309,
    "l": -4.7698
  },
  {
    "team": "Grambling State",
    "score": 0.3659,
    "w": 3.817,
    "l": -3.4511
  },
  {
    "team": "Southeast Missouri",
    "score": 0.1346,
    "w": 4.7487,
    "l": -4.6141
  },
  {
    "team": "Eastern Illinois",
    "score": 0.1063,
    "w": 4.9695,
    "l": -4.8632
  },
  {
    "team": "Youngstown State",
    "score": 0.0424,
    "w": 4.2861,
    "l": -4.2437
  },
  {
    "team": "Prairie View A&M",
    "score": 0.0403,
    "w": 5.2759,
    "l": -5.2356
  },
  {
    "team": "Houston Baptist",
    "score": -0.0873,
    "w": 6.1303,
    "l": -6.2176
  },
  {
    "team": "Stephen F. Austin",
    "score": -0.1618,
    "w": 3.2541,
    "l": -3.4159
  },
  {
    "team": "Nicholls State",
    "score": -0.2341,
    "w": 5.4123,
    "l": -5.6464
  },
  {
    "team": "Gardner-Webb",
    "score": -0.3198,
    "w": 4.6407,
    "l": -4.9605
  },
  {
    "team": "Holy Cross",
    "score": -0.4011,
    "w": 4.6315,
    "l": -5.0326
  },
  {
    "team": "Northern Colorado",
    "score": -0.4076,
    "w": 4.7287,
    "l": -5.1363
  },
  {
    "team": "Rhode Island",
    "score": -0.5262,
    "w": 5.1318,
    "l": -5.658
  },
  {
    "team": "Weber State",
    "score": -0.6144,
    "w": 4.5355,
    "l": -5.1499
  },
  {
    "team": "North Carolina Central",
    "score": -0.6221,
    "w": 3.7676,
    "l": -4.3897
  },
  {
    "team": "Stetson",
    "score": -0.7796,
    "w": 5.3731,
    "l": -6.1527
  },
  {
    "team": "Alabama State",
    "score": -1.4465,
    "w": 4.8597,
    "l": -6.3062
  },
  {
    "team": "Portland State",
    "score": -1.6574,
    "w": 5.1593,
    "l": -6.8167
  },
  {
    "team": "Western Carolina",
    "score": -1.6826,
    "w": 1.518,
    "l": -3.2006
  },
  {
    "team": "Furman",
    "score": -1.8214,
    "w": 1.7616,
    "l": -3.583
  },
  {
    "team": "Merrimack",
    "score": -1.9374,
    "w": 1.5973,
    "l": -3.5347
  },
  {
    "team": "Cornell",
    "score": -1.9867,
    "w": 3.5283,
    "l": -5.515
  },
  {
    "team": "Fordham",
    "score": -2.1234,
    "w": 5.6332,
    "l": -7.7566
  },
  {
    "team": "Illinois State",
    "score": -2.3049,
    "w": 2.3464,
    "l": -4.6513
  },
  {
    "team": "Lafayette",
    "score": -2.3669,
    "w": 4.8173,
    "l": -7.1842
  },
  {
    "team": "Sam Houston State",
    "score": -2.5406,
    "w": 3.3939,
    "l": -5.9345
  },
  {
    "team": "Arkansas-Pine Bluff",
    "score": -2.8727,
    "w": 5.3529,
    "l": -8.2256
  },
  {
    "team": "Duquesne",
    "score": -3.0289,
    "w": 2.5074,
    "l": -5.5363
  },
  {
    "team": "North Carolina A&T",
    "score": -3.1251,
    "w": 1,
    "l": -4.1251
  },
  {
    "team": "Kennesaw State",
    "score": -3.1313,
    "w": 4.0647,
    "l": -7.196
  },
  {
    "team": "North Dakota",
    "score": -3.4704,
    "w": 3.0124,
    "l": -6.4828
  },
  {
    "team": "Alcorn State",
    "score": -3.5539,
    "w": 2.4525,
    "l": -6.0064
  },
  {
    "team": "Southern",
    "score": -3.7853,
    "w": 1.7454,
    "l": -5.5307
  },
  {
    "team": "Morehead State",
    "score": -3.9067,
    "w": 3.4676,
    "l": -7.3743
  },
  {
    "team": "Sacred Heart",
    "score": -4.0544,
    "w": 2,
    "l": -6.0544
  },
  {
    "team": "Eastern Kentucky",
    "score": -4.0914,
    "w": 2.9896,
    "l": -7.081
  },
  {
    "team": "Bucknell",
    "score": -4.238,
    "w": 2.5417,
    "l": -6.7797
  },
  {
    "team": "North Dakota State",
    "score": -4.2411,
    "w": 4.2956,
    "l": -8.5367
  },
  {
    "team": "Colgate",
    "score": -4.3968,
    "w": 3.5684,
    "l": -7.9652
  },
  {
    "team": "Savannah State",
    "score": -4.4475,
    "w": 2.8103,
    "l": -7.2578
  },
  {
    "team": "Morgan State",
    "score": -4.473,
    "w": 0,
    "l": -4.473
  },
  {
    "team": "Eastern Washington",
    "score": -4.5816,
    "w": 1.7121,
    "l": -6.2937
  },
  {
    "team": "Princeton",
    "score": -4.6957,
    "w": 3.0535,
    "l": -7.7492
  },
  {
    "team": "Hampton",
    "score": -4.6985,
    "w": 2.7121,
    "l": -7.4106
  },
  {
    "team": "Sacramento State",
    "score": -4.771,
    "w": 3.0176,
    "l": -7.7886
  },
  {
    "team": "Wofford",
    "score": -5.0972,
    "w": 2.5911,
    "l": -7.6883
  },
  {
    "team": "North Alabama",
    "score": -5.3366,
    "w": 3.6736,
    "l": -9.0102
  },
  {
    "team": "James Madison",
    "score": -5.4451,
    "w": 1.5009,
    "l": -6.946
  },
  {
    "team": "Montana",
    "score": -5.4843,
    "w": 3.6768,
    "l": -9.1611
  },
  {
    "team": "Idaho",
    "score": -5.7626,
    "w": 2.4896,
    "l": -8.2522
  },
  {
    "team": "Albany",
    "score": -5.8239,
    "w": 3.0245,
    "l": -8.8484
  },
  {
    "team": "Norfolk State",
    "score": -5.9889,
    "w": 1.9614,
    "l": -7.9503
  },
  {
    "team": "Howard",
    "score": -5.9983,
    "w": 2.4679,
    "l": -8.4662
  },
  {
    "team": "Northern Arizona",
    "score": -6.1439,
    "w": 3.2451,
    "l": -9.389
  },
  {
    "team": "South Dakota",
    "score": -6.4749,
    "w": 0,
    "l": -6.4749
  },
  {
    "team": "Elon",
    "score": -6.5012,
    "w": 2.5437,
    "l": -9.0449
  },
  {
    "team": "Chattanooga",
    "score": -6.8392,
    "w": 1.856,
    "l": -8.6952
  },
  {
    "team": "Brown",
    "score": -6.9038,
    "w": 2.9257,
    "l": -9.8295
  },
  {
    "team": "Richmond",
    "score": -7.0542,
    "w": 2.731,
    "l": -9.7852
  },
  {
    "team": "Jacksonville",
    "score": -7.551,
    "w": 1.3883,
    "l": -8.9393
  },
  {
    "team": "Central Arkansas",
    "score": -8.2543,
    "w": 1.9473,
    "l": -10.2016
  },
  {
    "team": "William & Mary",
    "score": -8.5363,
    "w": 2.3531,
    "l": -10.8894
  },
  {
    "team": "Georgetown",
    "score": -8.7944,
    "w": 0,
    "l": -8.7944
  },
  {
    "team": "Idaho State",
    "score": -9.6845,
    "w": 1.734,
    "l": -11.4185
  },
  {
    "team": "East Tennessee State",
    "score": -10.2813,
    "w": 0,
    "l": -10.2813
  },
  {
    "team": "Central Connecticut",
    "score": -10.8978,
    "w": 0,
    "l": -10.8978
  },
  {
    "team": "UT Martin",
    "score": -12.6924,
    "w": 0,
    "l": -12.6924
  },
  {
    "team": "New Hampshire",
    "score": -13.6276,
    "w": 0,
    "l": -13.6276
  }
]